gradbench.py
gradbench-0.0.0.dist-info/LICENSE
gradbench-0.0.0.dist-info/METADATA
gradbench-0.0.0.dist-info/WHEEL
gradbench-0.0.0.dist-info/RECORD
